efai_parsing_dcmtags-0.1.0.dist-info/licenses/LICENSE
parsing_dcmtags_v2/__init__.py
parsing_dcmtags_v2/config.py
parsing_dcmtags_v2/file_scanner.py
parsing_dcmtags_v2/hierarchy_stats.py
parsing_dcmtags_v2/instance_export.py
parsing_dcmtags_v2/merge_batches.py
parsing_dcmtags_v2/series_export.py
parsing_dcmtags_v2/series_stats.py
parsing_dcmtags_v2/series_utils.py
parsing_dcmtags_v2/tag_extractor.py
efai_parsing_dcmtags-0.1.0.dist-info/METADATA
efai_parsing_dcmtags-0.1.0.dist-info/WHEEL
efai_parsing_dcmtags-0.1.0.dist-info/top_level.txt
efai_parsing_dcmtags-0.1.0.dist-info/RECORD
