Metadata-Version: 2.4
Name: efai-parsing-dcmtags
Version: 0.1.0
Summary: A package for handling DICOM tag extraction and batch merging
Author: Jocelyn
Author-email: cindysa110702@gmail.com
Classifier: Programming Language :: Python :: 3
Classifier: License :: OSI Approved :: MIT License
Classifier: Operating System :: OS Independent
Requires-Python: >=3.8
License-File: LICENSE
Requires-Dist: pandas
Requires-Dist: pydicom
Requires-Dist: tqdm
Requires-Dist: XlsxWriter
Requires-Dist: matplotlib
Requires-Dist: openpyxl
Dynamic: author
Dynamic: author-email
Dynamic: classifier
Dynamic: description
Dynamic: description-content-type
Dynamic: license-file
Dynamic: requires-dist
Dynamic: requires-python
Dynamic: summary
